{
    "skillcategorys": [
        {
            "categorytype": 0,
            "skilltypes": [
                {
                    "skillstage": [
                        {
                            "stage": 0,
                            "stageName": "AddStamina01"
                        },
                        {
                            "stage": 0,
                            "stageName": "EnhanceAutoHeal01"
                        },
                        {
                            "stage": 0,
                            "stageName": "AddStamina02"
                        },
                        {
                            "stage": 0,
                            "stageName": "EnhanceAutoHeal02"
                        },
                        {
                            "stage": 0,
                            "stageName": "AddStamina03"
                        }
                    ],
                    "typeName": "Stamina"
                },
                {
                    "skillstage": [
                        {
                            "stage": 0,
                            "stageName": "AddLife01"
                        },
                        {
                            "stage": 0,
                            "stageName": "AddLife02"
                        }
                    ],
                    "typeName": "Life"
                },
                {
                    "skillstage": [
                        {
                            "stage": 0,
                            "stageName": "SubNeedStamina01"
                        },
                        {
                            "stage": 0,
                            "stageName": "SubNeedStamina02"
                        },
                        {
                            "stage": 0,
                            "stageName": "HealStamina01"
                        },
                        {
                            "stage": 0,
                            "stageName": "HealStamina02"
                        },
                        {
                            "stage": 0,
                            "stageName": "SubNeedStamina03"
                        }
                    ],
                    "typeName": "Counter"
                },
                {
                    "skillstage": [
                        {
                            "stage": 0,
                            "stageName": "AddRespawnPercent"
                        }
                    ],
                    "typeName": "respawn"
                },
                {
                    "skillstage": [
                        {
                            "stage": 0,
                            "stageName": "SubNeedStamina01"
                        },
                        {
                            "stage": 0,
                            "stageName": "SubNeedStamina02"
                        },
                        {
                            "stage": 0,
                            "stageName": "KnockbackMitigation01"
                        },
                        {
                            "stage": 0,
                            "stageName": "KnockbackMitigation02"
                        }
                    ],
                    "typeName": "Guard"
                }
            ]
        },
        {
            "categorytype": 0,
            "skilltypes": [
                {
                    "skillstage": [
                        {
                            "stage": 0,
                            "stageName": "normalATK"
                        }
                    ],
                    "typeName": "AddCombo"
                },
                {
                    "skillstage": [
                        {
                            "stage": 0,
                            "stageName": "UnlockCounter"
                        }
                    ],
                    "typeName": "GetCounter"
                }
            ]
        }
    ]
}
